{"cluster_id": "cluster_1068", "topic": "中国赢得金牌", "abstract": "多哥国务部长兼卫生部长夏尔·孔迪·阿巴30日盛赞北京奥运会取得圆满成功。阿巴当天在机场迎接为多哥获得首枚奥运奖牌的布克佩蒂时接受了新华社记者的采访。中国首先在奥运会组织方面取得了成功。阿巴说。", "relate_article_list": ["2008-08-30-0002"], "keywords": ["奥运会", "多哥", "阿巴", "北京", "中国", "当天", "机场", "首枚", "布克", "赢得", "国务部长", "卫生部长", "夏尔", "孔迪", "佩蒂时", "铭刻", "记忆里", "去过", "佩蒂", "洛美", "格诺法梅"], "knowledge-data": {"nodes": {"1": {"name": "部长", "type": "nnt"}, "2": {"name": "北京", "type": "ns"}, "3": {"name": "洛美", "type": "ns"}, "4": {"name": "阿巴", "type": "nrf"}, "5": {"name": "奥运会", "type": "n"}, "6": {"name": "佩蒂", "type": "nrf"}, "7": {"name": "上", "type": "f"}, "8": {"name": "比赛", "type": "vn"}, "9": {"name": "这次", "type": "r"}, "10": {"name": "组织", "type": "n"}, "11": {"name": "人", "type": "n"}, "12": {"name": "获得", "type": "v"}, "13": {"name": "国务部长", "type": "nnt"}, "14": {"name": "多哥", "type": "ns"}, "15": {"name": "布克", "type": "nrf"}, "16": {"name": "金牌", "type": "n"}, "17": {"name": "记忆里", "type": "n"}, "18": {"name": "奖牌", "type": "n"}, "19": {"name": "我们", "type": "rr"}, "20": {"name": "格诺法梅", "type": "nrf"}, "21": {"name": "中国", "type": "ns"}}, "links": [{"source": "21", "target": "16", "rela": "赢得", "type": "svo"}, {"source": "5", "target": "18", "rela": "赢得", "type": "svo"}, {"source": "6", "target": "3", "rela": "回到", "type": "svo"}, {"source": "14", "target": "13", "rela": "修饰", "type": "att"}, {"source": "13", "target": "1", "rela": "修饰", "type": "att"}, {"source": "2", "target": "5", "rela": "修饰", "type": "att"}, {"source": "12", "target": "15", "rela": "修饰", "type": "att"}, {"source": "15", "target": "6", "rela": "修饰", "type": "att"}, {"source": "5", "target": "10", "rela": "修饰", "type": "att"}, {"source": "9", "target": "5", "rela": "修饰", "type": "att"}, {"source": "14", "target": "11", "rela": "修饰", "type": "att"}, {"source": "19", "target": "17", "rela": "修饰", "type": "att"}, {"source": "5", "target": "7", "rela": "修饰", "type": "att"}, {"source": "5", "target": "8", "rela": "修饰", "type": "att"}, {"source": "4", "target": "20", "rela": "修饰", "type": "att"}]}}