{"cluster_id": "cluster_158", "topic": "", "abstract": "上海环境能源交易所今天正式挂牌成立。这标志着我国节能减排和环境保护事业从单一的行政配置向市场化配置的重大转型。有利于完善能源资源节约和环境保护奖惩机制。有利于完成。节能减排约束性目标。", "relate_article_list": ["2008-08-05-0013"], "keywords": ["配置", "环境", "能源", "节能", "减排", "环境保护", "市场化", "有利于", "资源", "更", "交易所", "挂牌", "单一", "转型", "引入", "节约", "奖惩", "十一五", "约束性", "深层次", "更广"], "knowledge-data": {"nodes": {"1": {"name": "转型", "type": "vn"}, "2": {"name": "资源", "type": "n"}, "3": {"name": "奖惩", "type": "n"}, "4": {"name": "环境", "type": "n"}, "5": {"name": "市场化", "type": "vn"}, "6": {"name": "事业", "type": "n"}, "7": {"name": "配置", "type": "vn"}, "8": {"name": "减排", "type": "v"}, "9": {"name": "运行", "type": "vn"}, "10": {"name": "行政", "type": "n"}, "11": {"name": "节能", "type": "vn"}, "12": {"name": "重大", "type": "a"}, "13": {"name": "机制", "type": "n"}, "14": {"name": "目标", "type": "n"}, "15": {"name": "能源", "type": "n"}, "16": {"name": "约束性", "type": "nz"}, "17": {"name": "单一", "type": "a"}, "18": {"name": "优化", "type": "v"}}, "links": [{"source": "11", "target": "6", "rela": "修饰", "type": "att"}, {"source": "8", "target": "6", "rela": "修饰", "type": "att"}, {"source": "17", "target": "7", "rela": "修饰", "type": "att"}, {"source": "10", "target": "7", "rela": "修饰", "type": "att"}, {"source": "5", "target": "1", "rela": "修饰", "type": "att"}, {"source": "12", "target": "1", "rela": "修饰", "type": "att"}, {"source": "5", "target": "9", "rela": "修饰", "type": "att"}, {"source": "15", "target": "2", "rela": "修饰", "type": "att"}, {"source": "3", "target": "13", "rela": "修饰", "type": "att"}, {"source": "11", "target": "14", "rela": "修饰", "type": "att"}, {"source": "8", "target": "14", "rela": "修饰", "type": "att"}, {"source": "16", "target": "14", "rela": "修饰", "type": "att"}, {"source": "4", "target": "2", "rela": "修饰", "type": "att"}, {"source": "2", "target": "18", "rela": "修饰", "type": "att"}]}, "ex_im": {"配置": {"ex": 0.6412273333333333, "im": 0.0}, "环境": {"ex": 0.481148, "im": 0.0}, "能源": {"ex": 0.4817055, "im": 0.0}, "节能": {"ex": 0.31974933333333333, "im": 0.6412273333333333}, "减排": {"ex": 0.31974933333333333, "im": 0.31974933333333333}}, "start_time": "2008-08-05", "end_time": "2008-08-05", "timeline": {"2008-08-01": "0", "2008-08-02": "0", "2008-08-03": "0", "2008-08-04": "0", "2008-08-05": "1", "2008-08-06": "0", "2008-08-07": "0", "2008-08-08": "0", "2008-08-09": "0", "2008-08-10": "0", "2008-08-11": "0", "2008-08-12": "0", "2008-08-13": "0", "2008-08-14": "0", "2008-08-15": "0", "2008-08-16": "0", "2008-08-17": "0", "2008-08-18": "0", "2008-08-19": "0", "2008-08-20": "0", "2008-08-21": "0", "2008-08-22": "0", "2008-08-23": "0", "2008-08-24": "0", "2008-08-25": "0", "2008-08-26": "0", "2008-08-27": "0", "2008-08-28": "0", "2008-08-29": "0", "2008-08-30": "0", "2008-08-31": "0"}, "emotion": "0.9996878"}