{"cluster_id": "cluster_355", "topic": "官方网站提到选手", "abstract": "也为中国跳水。的奥运征程实现。并将优势一直保持到了比赛结束。在第四轮结束后。德国选手科齐安/菲舍尔和美国选手布赖恩特/里滕豪斯得分相同。而之后出场的美国选手仅仅获得72分。最终获铜牌。德国选手科齐安和菲舍尔相拥而泣。", "relate_article_list": ["2008-08-10-0028"], "keywords": ["选手", "分", "美国", "跳水", "德国", "郭晶晶", "吴敏霞", "名将", "科齐安", "菲舍尔", "布赖恩", "滕", "豪斯", "两名", "官方网站", "生于", "黄金搭档", "特出", "而里", "英凌级赛"], "knowledge-data": {"nodes": {"1": {"name": "跳水", "type": "vn"}, "2": {"name": "出场", "type": "vi"}, "3": {"name": "德国", "type": "nsf"}, "4": {"name": "两名", "type": "m"}, "5": {"name": "俄罗斯", "type": "nsf"}, "6": {"name": "名列第一", "type": "nz"}, "7": {"name": "布赖恩特/里滕豪斯", "type": "nrf"}, "8": {"name": "帕卡琳娜", "type": "nrf"}, "9": {"name": "分", "type": "qt"}, "10": {"name": "位", "type": "q"}, "11": {"name": "名将", "type": "n"}, "12": {"name": "选手", "type": "n"}, "13": {"name": "官方网站", "type": "nz"}, "14": {"name": "金牌", "type": "n"}, "15": {"name": "美国", "type": "nsf"}, "16": {"name": "科", "type": "n"}, "17": {"name": "联合会", "type": "nis"}, "18": {"name": "成绩", "type": "n"}, "19": {"name": "科齐安/菲舍尔", "type": "n"}, "20": {"name": "国际泳联", "type": "nt"}, "21": {"name": "343.50", "type": "m"}}, "links": [{"source": "13", "target": "12", "rela": "提到", "type": "svo"}, {"source": "1", "target": "14", "rela": "修饰", "type": "att"}, {"source": "21", "target": "9", "rela": "修饰", "type": "att"}, {"source": "9", "target": "6", "rela": "修饰", "type": "att"}, {"source": "5", "target": "11", "rela": "修饰", "type": "att"}, {"source": "11", "target": "8", "rela": "修饰", "type": "att"}, {"source": "3", "target": "12", "rela": "修饰", "type": "att"}, {"source": "12", "target": "19", "rela": "修饰", "type": "att"}, {"source": "15", "target": "12", "rela": "修饰", "type": "att"}, {"source": "12", "target": "7", "rela": "修饰", "type": "att"}, {"source": "2", "target": "12", "rela": "修饰", "type": "att"}, {"source": "12", "target": "18", "rela": "修饰", "type": "att"}, {"source": "4", "target": "12", "rela": "修饰", "type": "att"}, {"source": "1", "target": "17", "rela": "修饰", "type": "att"}, {"source": "17", "target": "13", "rela": "修饰", "type": "att"}, {"source": "10", "target": "12", "rela": "修饰", "type": "att"}, {"source": "12", "target": "16", "rela": "修饰", "type": "att"}, {"source": "20", "target": "13", "rela": "修饰", "type": "att"}]}, "ex_im": {"选手": {"ex": 0.43990825, "im": 0.0}, "分": {"ex": 0.32985033333333336, "im": 0.0}, "美国": {"ex": 0.65261375, "im": 0.33060466666666666}, "跳水": {"ex": 0.6030053333333333, "im": 0.0}, "德国": {"ex": 0.6515096666666667, "im": 0.43990825}}, "start_time": "2008-08-10", "end_time": "2008-08-10", "timeline": {"2008-08-01": "0", "2008-08-02": "0", "2008-08-03": "0", "2008-08-04": "0", "2008-08-05": "0", "2008-08-06": "0", "2008-08-07": "0", "2008-08-08": "0", "2008-08-09": "0", "2008-08-10": "1", "2008-08-11": "0", "2008-08-12": "0", "2008-08-13": "0", "2008-08-14": "0", "2008-08-15": "0", "2008-08-16": "0", "2008-08-17": "0", "2008-08-18": "0", "2008-08-19": "0", "2008-08-20": "0", "2008-08-21": "0", "2008-08-22": "0", "2008-08-23": "0", "2008-08-24": "0", "2008-08-25": "0", "2008-08-26": "0", "2008-08-27": "0", "2008-08-28": "0", "2008-08-29": "0", "2008-08-30": "0", "2008-08-31": "0"}, "emotion": "0.8982749"}