{"cluster_id": "cluster_1103", "topic": "奥尔默特会见阿巴斯", "abstract": "即在2009年前达成一项内容广泛的和平协议。", "relate_article_list": ["2008-08-31-0001"], "keywords": ["以色列", "总理", "奥尔默特", "耶路撒冷", "官邸", "会见", "巴勒斯坦民族权力机构", "阿巴斯", "两位", "领导人", "在会谈中", "和谈", "力争", "安纳波利斯", "中东问题", "会议", "承诺", "年前", "达成", "内容", "协议"], "knowledge-data": {"nodes": {"1": {"name": "作出", "type": "v"}, "2": {"name": "耶路撒冷", "type": "nsf"}, "3": {"name": "广泛", "type": "a"}, "4": {"name": "承诺", "type": "vn"}, "5": {"name": "总理", "type": "nnt"}, "6": {"name": "主席", "type": "nnt"}, "7": {"name": "一项", "type": "m"}, "8": {"name": "上", "type": "f"}, "9": {"name": "会议", "type": "n"}, "10": {"name": "和平", "type": "n"}, "11": {"name": "内容", "type": "n"}, "12": {"name": "美国安纳波利斯", "type": "nsf"}, "13": {"name": "以色列", "type": "nsf"}, "14": {"name": "国际", "type": "n"}, "15": {"name": "奥尔默特", "type": "nrf"}, "16": {"name": "阿巴斯", "type": "nrf"}, "17": {"name": "两位", "type": "m"}, "18": {"name": "官邸", "type": "n"}, "19": {"name": "中东问题", "type": "nz"}, "20": {"name": "协议", "type": "n"}, "21": {"name": "巴勒斯坦民族权力机构", "type": "nt"}, "22": {"name": "领导人", "type": "nnt"}}, "links": [{"source": "15", "target": "16", "rela": "会见", "type": "svo"}, {"source": "13", "target": "5", "rela": "修饰", "type": "att"}, {"source": "5", "target": "15", "rela": "修饰", "type": "att"}, {"source": "2", "target": "18", "rela": "修饰", "type": "att"}, {"source": "21", "target": "6", "rela": "修饰", "type": "att"}, {"source": "6", "target": "16", "rela": "修饰", "type": "att"}, {"source": "17", "target": "22", "rela": "修饰", "type": "att"}, {"source": "12", "target": "9", "rela": "修饰", "type": "att"}, {"source": "19", "target": "9", "rela": "修饰", "type": "att"}, {"source": "14", "target": "9", "rela": "修饰", "type": "att"}, {"source": "9", "target": "8", "rela": "修饰", "type": "att"}, {"source": "1", "target": "4", "rela": "修饰", "type": "att"}, {"source": "7", "target": "11", "rela": "修饰", "type": "att"}, {"source": "3", "target": "20", "rela": "修饰", "type": "att"}, {"source": "10", "target": "20", "rela": "修饰", "type": "att"}]}, "ex_im": {"以色列": {"ex": 0.1960335, "im": 0.0}, "总理": {"ex": 0.1960335, "im": 0.0}, "奥尔默特": {"ex": 0.1960335, "im": 0.0}, "耶路撒冷": {"ex": 0.1960335, "im": 0.0}, "官邸": {"ex": 0.1960335, "im": 0.0}}, "start_time": "2008-08-31", "end_time": "2008-08-31", "timeline": {"2008-08-01": "0", "2008-08-02": "0", "2008-08-03": "0", "2008-08-04": "0", "2008-08-05": "0", "2008-08-06": "0", "2008-08-07": "0", "2008-08-08": "0", "2008-08-09": "0", "2008-08-10": "0", "2008-08-11": "0", "2008-08-12": "0", "2008-08-13": "0", "2008-08-14": "0", "2008-08-15": "0", "2008-08-16": "0", "2008-08-17": "0", "2008-08-18": "0", "2008-08-19": "0", "2008-08-20": "0", "2008-08-21": "0", "2008-08-22": "0", "2008-08-23": "0", "2008-08-24": "0", "2008-08-25": "0", "2008-08-26": "0", "2008-08-27": "0", "2008-08-28": "0", "2008-08-29": "0", "2008-08-30": "0", "2008-08-31": "1"}, "emotion": "0.9999614"}