{"cluster_id": "cluster_88", "topic": "", "abstract": "中国第二十四次南极科考再传捷报。今天从南极中山站和中国气象科学研究院传来最新消息。中国南极中山站大气成分监测站。南极内陆考察队又在离中山站501公里的冰盖上建立了一个被命名为。中山站大气科考取得的进展。", "relate_article_list": ["2008-01-02-0041"], "keywords": ["南极", "中国", "中山站", "大气", "科考", "气象", "成分", "监测站", "冰盖", "自动", "第二十四", "传捷报", "最新消息", "第一组", "上风", "臭氧", "黑碳", "气溶胶", "一氧化碳", "氮氧化物", "仪器"], "EntityTopK": ["南极", "中山站", "中国", "大气", "项目"], "knowledge-data": {"nodes": {"1": {"name": "仪器", "type": "n"}, "2": {"name": "离", "type": "v"}, "3": {"name": "第二十四", "type": "mq"}, "4": {"name": "冰盖", "type": "n"}, "5": {"name": "地面", "type": "n"}, "6": {"name": "臭氧", "type": "n"}, "7": {"name": "气溶胶", "type": "gc"}, "8": {"name": "系统", "type": "n"}, "9": {"name": "在线", "type": "vn"}, "10": {"name": "记录", "type": "v"}, "11": {"name": "科考", "type": "n"}, "12": {"name": "上", "type": "f"}, "13": {"name": "业务", "type": "n"}, "14": {"name": "成分", "type": "n"}, "15": {"name": "气象", "type": "n"}, "16": {"name": "次", "type": "qv"}, "17": {"name": "中国", "type": "ns"}, "18": {"name": "监测站", "type": "nis"}, "19": {"name": "传捷报", "type": "n"}, "20": {"name": "资料", "type": "n"}, "21": {"name": "中国南极", "type": "ns"}, "22": {"name": "公里", "type": "q"}, "23": {"name": "方向", "type": "n"}, "24": {"name": "接轨", "type": "vi"}, "25": {"name": "齐全", "type": "a"}, "26": {"name": "中山站", "type": "ns"}, "27": {"name": "大气", "type": "n"}, "28": {"name": "南极", "type": "ns"}, "29": {"name": "内陆", "type": "s"}, "30": {"name": "上风", "type": "n"}, "31": {"name": "黑碳", "type": "nz"}, "32": {"name": "数字", "type": "n"}, "33": {"name": "自动", "type": "d"}}, "links": [{"source": "17", "target": "11", "rela": "修饰", "type": "att"}, {"source": "3", "target": "16", "rela": "修饰", "type": "att"}, {"source": "16", "target": "11", "rela": "修饰", "type": "att"}, {"source": "28", "target": "11", "rela": "修饰", "type": "att"}, {"source": "11", "target": "19", "rela": "修饰", "type": "att"}, {"source": "28", "target": "26", "rela": "修饰", "type": "att"}, {"source": "21", "target": "26", "rela": "修饰", "type": "att"}, {"source": "26", "target": "18", "rela": "修饰", "type": "att"}, {"source": "27", "target": "14", "rela": "修饰", "type": "att"}, {"source": "14", "target": "18", "rela": "修饰", "type": "att"}, {"source": "28", "target": "4", "rela": "修饰", "type": "att"}, {"source": "4", "target": "8", "rela": "修饰", "type": "att"}, {"source": "28", "target": "29", "rela": "修饰", "type": "att"}, {"source": "2", "target": "4", "rela": "修饰", "type": "att"}, {"source": "22", "target": "4", "rela": "修饰", "type": "att"}, {"source": "4", "target": "12", "rela": "修饰", "type": "att"}, {"source": "15", "target": "20", "rela": "修饰", "type": "att"}, {"source": "30", "target": "23", "rela": "修饰", "type": "att"}, {"source": "25", "target": "18", "rela": "修饰", "type": "att"}, {"source": "28", "target": "14", "rela": "修饰", "type": "att"}, {"source": "14", "target": "13", "rela": "修饰", "type": "att"}, {"source": "13", "target": "18", "rela": "修饰", "type": "att"}, {"source": "5", "target": "6", "rela": "修饰", "type": "att"}, {"source": "31", "target": "7", "rela": "修饰", "type": "att"}, {"source": "24", "target": "1", "rela": "修饰", "type": "att"}, {"source": "9", "target": "1", "rela": "修饰", "type": "att"}, {"source": "33", "target": "32", "rela": "修饰", "type": "att"}, {"source": "10", "target": "1", "rela": "修饰", "type": "att"}, {"source": "26", "target": "11", "rela": "修饰", "type": "att"}, {"source": "27", "target": "11", "rela": "修饰", "type": "att"}]}}