{"cluster_id": "cluster_799", "topic": "陈德铭说栏增加", "abstract": "猪肉等重要副食品价格大幅度上涨。去年年末200家企业的仔猪存栏数量比去年10月末增加0.3%。保障重要商品市场供应。一是加强市场运行监测。鼓励企业积极组织重要商品货源。增加市场供应。增加重要商品市场供应。", "relate_article_list": ["2008-01-20-0016"], "keywords": ["商品", "市场", "价格", "增加", "企业", "商务部", "运行", "市场供应", "猪肉", "春节", "去年", "投放", "陈德铭", "饲料", "副食品", "上涨", "生猪", "存栏", "母猪", "监测", "储备"], "EntityTopK": ["市场", "商品", "企业", "价格", "市场供应"], "knowledge-data": {"nodes": {"1": {"name": "因素", "type": "n"}, "2": {"name": "商务部", "type": "nis"}, "3": {"name": "资源", "type": "n"}, "4": {"name": "猪肉", "type": "nf"}, "5": {"name": "增加", "type": "v"}, "6": {"name": "企业", "type": "n"}, "7": {"name": "市场供应", "type": "nz"}, "8": {"name": "监测", "type": "vn"}, "9": {"name": "个", "type": "q"}, "10": {"name": "存栏", "type": "vi"}, "11": {"name": "家", "type": "q"}, "12": {"name": "春节", "type": "t"}, "13": {"name": "充分发挥", "type": "nz"}, "14": {"name": "数量", "type": "n"}, "15": {"name": "国内外", "type": "s"}, "16": {"name": "食用油", "type": "n"}, "17": {"name": "制度", "type": "n"}, "18": {"name": "供应量", "type": "n"}, "19": {"name": "一定", "type": "b"}, "20": {"name": "作用", "type": "n"}, "21": {"name": "去年", "type": "t"}, "22": {"name": "年末", "type": "t"}, "23": {"name": "10月末", "type": "t"}, "24": {"name": "国际", "type": "n"}, "25": {"name": "其他", "type": "rzv"}, "26": {"name": "市场", "type": "n"}, "27": {"name": "栏", "type": "n"}, "28": {"name": "即将来临", "type": "ns"}, "29": {"name": "副食品", "type": "n"}, "30": {"name": "商品", "type": "n"}, "31": {"name": "百姓生活", "type": "nz"}, "32": {"name": "仔猪", "type": "n"}, "33": {"name": "全国", "type": "n"}, "34": {"name": "价格", "type": "n"}, "35": {"name": "流通", "type": "vn"}, "36": {"name": "生猪", "type": "n"}, "37": {"name": "期间", "type": "f"}, "38": {"name": "投放", "type": "v"}, "39": {"name": "重要", "type": "a"}, "40": {"name": "母猪", "type": "n"}, "41": {"name": "部长", "type": "nnt"}, "42": {"name": "养殖", "type": "vn"}, "43": {"name": "余缺", "type": "n"}, "44": {"name": "货源", "type": "n"}, "45": {"name": "深入开展", "type": "i"}, "46": {"name": "大型", "type": "b"}, "47": {"name": "饲料", "type": "n"}, "48": {"name": "上涨", "type": "vi"}, "49": {"name": "陈德铭", "type": "nr"}}, "links": [{"source": "49", "target": "5", "rela": "说", "type": "svo"}, {"source": "20", "target": "7", "rela": "增加", "type": "svo"}, {"source": "2", "target": "38", "rela": "会同", "type": "svo"}, {"source": "2", "target": "41", "rela": "修饰", "type": "att"}, {"source": "41", "target": "49", "rela": "修饰", "type": "att"}, {"source": "4", "target": "30", "rela": "修饰", "type": "att"}, {"source": "39", "target": "30", "rela": "修饰", "type": "att"}, {"source": "30", "target": "31", "rela": "修饰", "type": "att"}, {"source": "12", "target": "28", "rela": "修饰", "type": "att"}, {"source": "24", "target": "34", "rela": "修饰", "type": "att"}, {"source": "4", "target": "29", "rela": "修饰", "type": "att"}, {"source": "39", "target": "29", "rela": "修饰", "type": "att"}, {"source": "29", "target": "34", "rela": "修饰", "type": "att"}, {"source": "36", "target": "10", "rela": "修饰", "type": "att"}, {"source": "40", "target": "27", "rela": "修饰", "type": "att"}, {"source": "26", "target": "18", "rela": "修饰", "type": "att"}, {"source": "33", "target": "6", "rela": "修饰", "type": "att"}, {"source": "11", "target": "6", "rela": "修饰", "type": "att"}, {"source": "46", "target": "6", "rela": "修饰", "type": "att"}, {"source": "42", "target": "6", "rela": "修饰", "type": "att"}, {"source": "21", "target": "22", "rela": "修饰", "type": "att"}, {"source": "6", "target": "32", "rela": "修饰", "type": "att"}, {"source": "32", "target": "10", "rela": "修饰", "type": "att"}, {"source": "10", "target": "14", "rela": "修饰", "type": "att"}, {"source": "21", "target": "23", "rela": "修饰", "type": "att"}, {"source": "47", "target": "34", "rela": "修饰", "type": "att"}, {"source": "34", "target": "1", "rela": "修饰", "type": "att"}, {"source": "4", "target": "34", "rela": "修饰", "type": "att"}, {"source": "16", "target": "34", "rela": "修饰", "type": "att"}, {"source": "25", "target": "34", "rela": "修饰", "type": "att"}, {"source": "19", "target": "48", "rela": "修饰", "type": "att"}, {"source": "30", "target": "7", "rela": "修饰", "type": "att"}, {"source": "8", "target": "17", "rela": "修饰", "type": "att"}, {"source": "30", "target": "43", "rela": "修饰", "type": "att"}, {"source": "13", "target": "6", "rela": "修饰", "type": "att"}, {"source": "35", "target": "6", "rela": "修饰", "type": "att"}, {"source": "6", "target": "20", "rela": "修饰", "type": "att"}, {"source": "30", "target": "44", "rela": "修饰", "type": "att"}, {"source": "12", "target": "37", "rela": "修饰", "type": "att"}, {"source": "15", "target": "26", "rela": "修饰", "type": "att"}, {"source": "9", "target": "26", "rela": "修饰", "type": "att"}, {"source": "26", "target": "3", "rela": "修饰", "type": "att"}, {"source": "45", "target": "26", "rela": "修饰", "type": "att"}, {"source": "30", "target": "26", "rela": "修饰", "type": "att"}]}}