{"cluster_id": "cluster_1036", "topic": "据格鲁吉亚新闻通讯社断绝外交关系", "abstract": "格鲁吉亚副外长瓦沙泽29日对媒体表示。格将中断与俄罗斯的外交关系。据格鲁吉亚新闻通讯社29日援引格副外长瓦沙泽29日的话说。格鲁吉亚将断绝与俄罗斯的外交关系。瓦沙泽说。断绝外交关系并不意味着领事关系也要自动断绝。", "relate_article_list": ["2008-08-29-0003"], "keywords": ["格鲁吉亚", "格", "俄罗斯", "外交关系", "断绝", "领事", "俄", "副外长", "瓦沙泽", "议会", "保留", "机构", "驻格", "外交部", "断交", "瓦沙泽说", "维也纳", "科瓦连科", "照会", "占领军", "俄在格"], "knowledge-data": {"nodes": {"1": {"name": "照会", "type": "n"}, "2": {"name": "国", "type": "n"}, "3": {"name": "我们", "type": "rr"}, "4": {"name": "外交关系", "type": "nz"}, "5": {"name": "外长", "type": "nnt"}, "6": {"name": "瓦沙泽", "type": "n"}, "7": {"name": "公约", "type": "n"}, "8": {"name": "机构", "type": "n"}, "9": {"name": "科瓦连科", "type": "nrf"}, "10": {"name": "与", "type": "cc"}, "11": {"name": "领事", "type": "nnt"}, "12": {"name": "据格鲁吉亚新闻通讯社", "type": "p"}, "13": {"name": "代表", "type": "nnt"}, "14": {"name": "俄", "type": "b"}, "15": {"name": "关于", "type": "p"}, "16": {"name": "发出", "type": "v"}, "17": {"name": "保留", "type": "v"}, "18": {"name": "格鲁吉亚", "type": "nsf"}, "19": {"name": "维也纳", "type": "nsf"}, "20": {"name": "维和部队", "type": "nz"}, "21": {"name": "断交", "type": "vi"}, "22": {"name": "29日", "type": "m"}, "23": {"name": "格", "type": "b"}, "24": {"name": "关系", "type": "n"}, "25": {"name": "领土", "type": "n"}, "26": {"name": "大使", "type": "nnt"}}, "links": [{"source": "12", "target": "4", "rela": "断绝", "type": "svo"}, {"source": "3", "target": "8", "rela": "保留", "type": "svo"}, {"source": "9", "target": "21", "rela": "表示", "type": "svo"}, {"source": "18", "target": "5", "rela": "修饰", "type": "att"}, {"source": "5", "target": "6", "rela": "修饰", "type": "att"}, {"source": "10", "target": "4", "rela": "修饰", "type": "att"}, {"source": "23", "target": "5", "rela": "修饰", "type": "att"}, {"source": "6", "target": "22", "rela": "修饰", "type": "att"}, {"source": "23", "target": "2", "rela": "修饰", "type": "att"}, {"source": "17", "target": "8", "rela": "修饰", "type": "att"}, {"source": "13", "target": "8", "rela": "修饰", "type": "att"}, {"source": "11", "target": "8", "rela": "修饰", "type": "att"}, {"source": "19", "target": "7", "rela": "修饰", "type": "att"}, {"source": "11", "target": "24", "rela": "修饰", "type": "att"}, {"source": "26", "target": "9", "rela": "修饰", "type": "att"}, {"source": "16", "target": "1", "rela": "修饰", "type": "att"}, {"source": "15", "target": "1", "rela": "修饰", "type": "att"}, {"source": "23", "target": "25", "rela": "修饰", "type": "att"}, {"source": "14", "target": "20", "rela": "修饰", "type": "att"}]}, "emotion": "0.7114328", "timeline": {"2008-08-01": "0", "2008-08-02": "0", "2008-08-03": "0", "2008-08-04": "0", "2008-08-05": "0", "2008-08-06": "0", "2008-08-07": "0", "2008-08-08": "0", "2008-08-09": "0", "2008-08-10": "0", "2008-08-11": "0", "2008-08-12": "0", "2008-08-13": "0", "2008-08-14": "0", "2008-08-15": "0", "2008-08-16": "0", "2008-08-17": "0", "2008-08-18": "0", "2008-08-19": "0", "2008-08-20": "0", "2008-08-21": "0", "2008-08-22": "0", "2008-08-23": "0", "2008-08-24": "0", "2008-08-25": "0", "2008-08-26": "0", "2008-08-27": "0", "2008-08-28": "0", "2008-08-29": "1", "2008-08-30": "0", "2008-08-31": "0"}, "start_time": "2008-08-29", "end_time": "2008-08-29"}